<annotation>
	<folder>my-project-name</folder>
	<filename>303809.jpg</filename>
	<path>/my-project-name/303809.jpg</path>
	<source>
		<database>Unspecified</database>
	</source>
	<size>
		<width>512</width>
		<height>384</height>
		<depth>3</depth>
	</size>
	<object>
		<name>french_fries</name>
		<pose>Unspecified</pose>
		<truncated>0</truncated>
		<difficult>0</difficult>
		<bndbox>
			<xmin>5</xmin>
			<ymin>38</ymin>
			<xmax>503</xmax>
			<ymax>365</ymax>
		</bndbox>
	</object>
</annotation>